LICENSE
MANIFEST.in
README.md
setup.py
django_facebook_connect.egg-info/PKG-INFO
django_facebook_connect.egg-info/SOURCES.txt
django_facebook_connect.egg-info/dependency_links.txt
django_facebook_connect.egg-info/not-zip-safe
django_facebook_connect.egg-info/requires.txt
django_facebook_connect.egg-info/top_level.txt
facebook_connect/__init__.py
facebook_connect/models.py
facebook_connect/urls.py
facebook_connect/views.py
facebook_connect/facebook_python_sdk/__init__.py
facebook_connect/facebook_python_sdk/facebook.py
facebook_connect/templates/channel.html
facebook_connect/templatetags/__init__.py
facebook_connect/templatetags/facebook_connect.py