Metadata-Version: 1.0
Name: django-facebook-connect
Version: 1.0
Summary: Add facebook connect authentication to your Django website.
Home-page: http://github.com/noamsu/django-facebook-connect
Author: Noam Sutskever
Author-email: noamsu@gmail.com
License: MIT
Download-URL: http://github.com/noamsu/django-facebook-connect/downloads
Platform: UNKNOWN
Classifier: Environment :: Web Environment
Classifier: Intended Audience :: Developers
Classifier: License :: OSI Approved :: MIT License
Classifier: Operating System :: OS Independent
Classifier: Programming Language :: Python
Classifier: Framework :: Django
